{
  "generated_at": "2026-05-19T22:20:27.679801+00:00",
  "insight": "Raw data summary: NASDAQ -0.84%, S&P 500 -0.67%, KOSPI +0.31%, USD/KRW +0.73%",
  "errors": [],
  "items": [
    {
      "key": "NASDAQ",
      "label": "NASDAQ",
      "price": 25870.708984375,
      "dod": -0.8432936925186103,
      "mom": 5.730754377722232,
      "yoy": 34.63486027486818,
      "raw_points": 1255
    },
    {
      "key": "S&P500",
      "label": "S&P 500",
      "price": 7353.60986328125,
      "dod": -0.6678320788135907,
      "mom": 3.1932063835623135,
      "yoy": 23.308232323815385,
      "raw_points": 1255
    },
    {
      "key": "KOSPI",
      "label": "KOSPI",
      "price": 7516.0400390625,
      "dod": 0.3050755853320529,
      "mom": 21.384645374847448,
      "yoy": 186.1214945453667,
      "raw_points": 1221
    },
    {
      "key": "KOSDAQ",
      "label": "KOSDAQ",
      "price": 1111.0899658203125,
      "dod": -1.6577845461366962,
      "mom": -5.038295380850515,
      "yoy": 53.23899135211132,
      "raw_points": 1220
    },
    {
      "key": "SET Index",
      "label": "SET Index",
      "price": 1517.739990234375,
      "dod": -0.013831874847909691,
      "mom": 2.380521449280852,
      "yoy": 26.92574370022585,
      "raw_points": 1207
    },
    {
      "key": "BTC/USD",
      "label": "BTC/USD",
      "price": 76660.25,
      "dod": -0.3819440425886592,
      "mom": 3.7964215374587473,
      "yoy": -27.409314277965652,
      "raw_points": 1827
    },
    {
      "key": "BTC/KRW",
      "label": "BTC/KRW",
      "price": 115547912.0,
      "dod": 0.5488963804318966,
      "mom": 6.707423882755393,
      "yoy": -21.25942600648286,
      "raw_points": 1827
    },
    {
      "key": "DXY",
      "label": "Dollar Index",
      "price": 99.30799865722656,
      "dod": 0.3415150372381053,
      "mom": 1.231396739954222,
      "yoy": -1.1171976944536512,
      "raw_points": 1258
    },
    {
      "key": "USD/JPY",
      "label": "USD/JPY",
      "price": 159.11,
      "dod": 0.21414624929143,
      "mom": -0.012568340350645267,
      "yoy": 9.753742153549021,
      "raw_points": 1280
    },
    {
      "key": "USD/KRW",
      "label": "USD/KRW",
      "price": 1508.75,
      "dod": 0.7310722392842867,
      "mom": 2.0121839904258985,
      "yoy": 8.638517259753167,
      "raw_points": 1280
    },
    {
      "key": "USD/THB",
      "label": "USD/THB",
      "price": 32.66,
      "dod": 0.1994170885105008,
      "mom": 1.8238503507404322,
      "yoy": -1.1949780668582761,
      "raw_points": 1280
    },
    {
      "key": "THB/KRW",
      "label": "THB/KRW",
      "price": 46.196,
      "dod": 0.5331766446867259,
      "mom": 0.1865105183257396,
      "yoy": 9.953824915504343,
      "raw_points": 1280
    }
  ]
}