{
  "generated_at": "2026-02-25T21:55:23.091276+00:00",
  "insight": "Raw data summary: NASDAQ +1.26%, S&P 500 +0.81%, KOSPI +1.91%, USD/KRW -0.21%",
  "errors": [],
  "items": [
    {
      "key": "NASDAQ",
      "label": "NASDAQ",
      "price": 23152.078125,
      "dod": 1.2613824259341457,
      "mom": -1.9036244601906536,
      "yoy": 21.6840260526292,
      "raw_points": 1255
    },
    {
      "key": "S&P500",
      "label": "S&P 500",
      "price": 6946.1298828125,
      "dod": 0.8136355657340022,
      "mom": -0.05899225878527654,
      "yoy": 16.638762147894713,
      "raw_points": 1255
    },
    {
      "key": "KOSPI",
      "label": "KOSPI",
      "price": 6083.85986328125,
      "dod": 1.9133435843133015,
      "mom": 22.916444702252,
      "yoy": 131.29996209276172,
      "raw_points": 1223
    },
    {
      "key": "KOSDAQ",
      "label": "KOSDAQ",
      "price": 1165.25,
      "dod": 0.02145922746781116,
      "mom": 9.47378947794561,
      "yoy": 51.44327763305784,
      "raw_points": 1222
    },
    {
      "key": "SET Index",
      "label": "SET Index",
      "price": 1516.010009765625,
      "dod": 1.7183296384895617,
      "mom": 15.985377375539073,
      "yoy": 25.664999822417794,
      "raw_points": 1207
    },
    {
      "key": "BTC/USD",
      "label": "BTC/USD",
      "price": 69075.2890625,
      "dod": 7.795322634515147,
      "mom": -21.742917496371543,
      "yoy": -22.15655960479758,
      "raw_points": 1827
    },
    {
      "key": "BTC/KRW",
      "label": "BTC/KRW",
      "price": 98524192.0,
      "dod": 6.697668752965684,
      "mom": -22.597588566525594,
      "yoy": -22.38320256157936,
      "raw_points": 1827
    },
    {
      "key": "DXY",
      "label": "Dollar Index",
      "price": 97.6500015258789,
      "dod": -0.2349772517295724,
      "mom": 0.6286073831373558,
      "yoy": -8.145984603133686,
      "raw_points": 1258
    },
    {
      "key": "USD/JPY",
      "label": "USD/JPY",
      "price": 155.33,
      "dod": 0.8374448195274088,
      "mom": -1.7644826713888135,
      "yoy": 2.792667593144066,
      "raw_points": 262
    },
    {
      "key": "USD/KRW",
      "label": "USD/KRW",
      "price": 1443.48,
      "dod": -0.20946968911379615,
      "mom": -1.80408163265306,
      "yoy": 0.26534042760095694,
      "raw_points": 262
    },
    {
      "key": "USD/THB",
      "label": "USD/THB",
      "price": 31.041,
      "dod": -0.5733504163997389,
      "mom": -0.44899137295147873,
      "yoy": -7.81361368496079,
      "raw_points": 262
    },
    {
      "key": "THB/KRW",
      "label": "THB/KRW",
      "price": 46.503,
      "dod": 0.3690753690753677,
      "mom": -1.3596640081452533,
      "yoy": 8.766226172377493,
      "raw_points": 262
    }
  ]
}