{
  "generated_at": "2026-07-10T17:26:07.252050+00:00",
  "insight": "Raw data summary: NASDAQ +0.22%, S&P 500 +0.30%, KOSPI +0.62%, USD/KRW -0.21%",
  "errors": [],
  "items": [
    {
      "key": "NASDAQ",
      "label": "NASDAQ",
      "price": 26265.470703125,
      "dod": 0.2235292960284181,
      "mom": 4.354360250004966,
      "yoy": 27.312798059774885,
      "raw_points": 1255
    },
    {
      "key": "S&P500",
      "label": "S&P 500",
      "price": 7565.9501953125,
      "dod": 0.29574659169060236,
      "mom": 4.113944718452097,
      "yoy": 20.468090591618253,
      "raw_points": 1255
    },
    {
      "key": "KOSPI",
      "label": "KOSPI",
      "price": 7291.91015625,
      "dod": 0.6226221119183561,
      "mom": -9.94228679332258,
      "yoy": 132.69033739154062,
      "raw_points": 1220
    },
    {
      "key": "KOSDAQ",
      "label": "KOSDAQ",
      "price": 794.0,
      "dod": 1.1464968152866242,
      "mom": -17.959103336093698,
      "yoy": 0.4605514848804464,
      "raw_points": 1219
    },
    {
      "key": "SET Index",
      "label": "SET Index",
      "price": 1611.280029296875,
      "dod": 1.1119738228606288,
      "mom": 1.4621594805228348,
      "yoy": 42.9440907314884,
      "raw_points": 1203
    },
    {
      "key": "BTC/USD",
      "label": "BTC/USD",
      "price": 63993.16015625,
      "dod": 1.2659785728847432,
      "mom": 4.1397893003491575,
      "yoy": -44.82739609878838,
      "raw_points": 1827
    },
    {
      "key": "BTC/KRW",
      "label": "BTC/KRW",
      "price": 96182200.0,
      "dod": 1.0700613661350196,
      "mom": 2.6118766060343708,
      "yoy": -39.63144819048118,
      "raw_points": 1827
    },
    {
      "key": "DXY",
      "label": "Dollar Index",
      "price": 100.85199737548828,
      "dod": -0.08718551990233409,
      "mom": 0.9024516806270468,
      "yoy": 3.279053558192512,
      "raw_points": 1257
    },
    {
      "key": "USD/JPY",
      "label": "USD/JPY",
      "price": 161.57989,
      "dod": -0.5045343497583819,
      "mom": 0.629548549928967,
      "yoy": 10.490286448895302,
      "raw_points": 5000
    },
    {
      "key": "USD/KRW",
      "label": "USD/KRW",
      "price": 1502.45439,
      "dod": -0.20995665473774253,
      "mom": -1.332419220221761,
      "yoy": 9.561044151582639,
      "raw_points": 5000
    },
    {
      "key": "USD/THB",
      "label": "USD/THB",
      "price": 33.315,
      "dod": -0.3886978621617658,
      "mom": 1.0923987255348184,
      "yoy": 2.146251724666551,
      "raw_points": 1282
    },
    {
      "key": "THB/KRW",
      "label": "THB/KRW",
      "price": 45.172,
      "dod": -0.11277447316631345,
      "mom": -2.3519239083441437,
      "yoy": 7.284170526065789,
      "raw_points": 1282
    }
  ]
}