{
  "generated_at": "2026-04-23T21:44:50.570193+00:00",
  "insight": "Raw data summary: NASDAQ -0.89%, S&P 500 -0.41%, KOSPI +0.46%, USD/KRW +0.09%",
  "errors": [],
  "items": [
    {
      "key": "NASDAQ",
      "label": "NASDAQ",
      "price": 24438.50390625,
      "dod": -0.8884346814128141,
      "mom": 12.299543855693834,
      "yoy": 46.267833550489435,
      "raw_points": 1255
    },
    {
      "key": "S&P500",
      "label": "S&P 500",
      "price": 7108.39990234375,
      "dod": -0.4132868267081413,
      "mom": 8.419747135829107,
      "yoy": 32.22814736850327,
      "raw_points": 1255
    },
    {
      "key": "KOSPI",
      "label": "KOSPI",
      "price": 6417.93017578125,
      "dod": 0.46114265147623507,
      "mom": 18.724139588054385,
      "yoy": 158.096485741134,
      "raw_points": 1222
    },
    {
      "key": "KOSDAQ",
      "label": "KOSDAQ",
      "price": 1181.1199951171875,
      "dod": 0.17726145801043505,
      "mom": 7.678981424199255,
      "yoy": 64.93325185312084,
      "raw_points": 1221
    },
    {
      "key": "SET Index",
      "label": "SET Index",
      "price": 1479.739990234375,
      "dod": -0.253455326297607,
      "mom": 5.89692032215577,
      "yoy": 29.342242653641282,
      "raw_points": 1207
    },
    {
      "key": "BTC/USD",
      "label": "BTC/USD",
      "price": 78091.9609375,
      "dod": -0.14211792471066675,
      "mom": 10.740685593166448,
      "yoy": -16.656666793957985,
      "raw_points": 1827
    },
    {
      "key": "BTC/KRW",
      "label": "BTC/KRW",
      "price": 115542072.0,
      "dod": -0.1014288646047086,
      "mom": 9.347881899288488,
      "yoy": -13.613951815841945,
      "raw_points": 1827
    },
    {
      "key": "DXY",
      "label": "Dollar Index",
      "price": 98.7969970703125,
      "dod": 0.20996119293121362,
      "mom": -0.636632035522915,
      "yoy": -1.0446707790816423,
      "raw_points": 1258
    },
    {
      "key": "USD/JPY",
      "label": "USD/JPY",
      "price": 159.48,
      "dod": 0.16329606833311827,
      "mom": 0.34606430503994395,
      "yoy": 12.595312058740474,
      "raw_points": 1282
    },
    {
      "key": "USD/KRW",
      "label": "USD/KRW",
      "price": 1479.36,
      "dod": 0.08863028990899803,
      "mom": -1.300988751451103,
      "yoy": 4.024245322157594,
      "raw_points": 1282
    },
    {
      "key": "USD/THB",
      "label": "USD/THB",
      "price": 32.355,
      "dod": 0.46576618537493736,
      "mom": -0.9338640538885479,
      "yoy": -3.0271242319796348,
      "raw_points": 1282
    },
    {
      "key": "THB/KRW",
      "label": "THB/KRW",
      "price": 45.723,
      "dod": -0.3747684932999327,
      "mom": -0.3704268624844785,
      "yoy": 7.270551801801793,
      "raw_points": 1282
    }
  ]
}