{
  "generated_at": "2026-04-14T14:12:05.874599+00:00",
  "insight": "Raw data summary: NASDAQ +1.02%, S&P 500 +0.61%, KOSPI +2.74%, USD/KRW +0.45%",
  "errors": [],
  "items": [
    {
      "key": "NASDAQ",
      "label": "NASDAQ",
      "price": 23419.232421875,
      "dod": 1.0157644328279307,
      "mom": 5.943685531577113,
      "yoy": 39.139468244377454,
      "raw_points": 1256
    },
    {
      "key": "S&P500",
      "label": "S&P 500",
      "price": 6928.39013671875,
      "dod": 0.6120887582943227,
      "mom": 4.4660994019977585,
      "yoy": 28.161825932646263,
      "raw_points": 1256
    },
    {
      "key": "KOSPI",
      "label": "KOSPI",
      "price": 5967.75,
      "dod": 2.739547080065373,
      "mom": 8.756856727628408,
      "yoy": 142.9974575828895,
      "raw_points": 1223
    },
    {
      "key": "KOSDAQ",
      "label": "KOSDAQ",
      "price": 1121.8800048828125,
      "dod": 2.003931457979116,
      "mom": -2.695666554579712,
      "yoy": 58.23860134119288,
      "raw_points": 1222
    },
    {
      "key": "SET Index",
      "label": "SET Index",
      "price": 1506.8399658203125,
      "dod": 1.1532786841586637,
      "mom": 7.070075633217969,
      "yoy": 32.88416867632263,
      "raw_points": 1208
    },
    {
      "key": "BTC/USD",
      "label": "BTC/USD",
      "price": 75409.25,
      "dod": 1.241342332112514,
      "mom": 3.5984874707379726,
      "yoy": -10.803030949895142,
      "raw_points": 1827
    },
    {
      "key": "BTC/KRW",
      "label": "BTC/KRW",
      "price": 110887016.0,
      "dod": 0.7296185495881757,
      "mom": 1.4327605184276515,
      "yoy": -7.659302773250046,
      "raw_points": 1827
    },
    {
      "key": "DXY",
      "label": "Dollar Index",
      "price": 13.14,
      "dod": 0.4587155963302791,
      "mom": 0.612557427258806,
      "yoy": 12.4037639007699,
      "raw_points": 5000
    },
    {
      "key": "USD/JPY",
      "label": "USD/JPY",
      "price": 158.69874,
      "dod": -0.4725053583469836,
      "mom": -0.603554788325542,
      "yoy": 10.985893350171787,
      "raw_points": 5000
    },
    {
      "key": "USD/KRW",
      "label": "USD/KRW",
      "price": 1489.95,
      "dod": 0.45035630734795845,
      "mom": -0.11731581417175035,
      "yoy": 4.070043585158693,
      "raw_points": 1280
    },
    {
      "key": "USD/THB",
      "label": "USD/THB",
      "price": 32.29,
      "dod": 0.5919003115264726,
      "mom": 0.2795031055900506,
      "yoy": -3.7699299657279113,
      "raw_points": 1280
    },
    {
      "key": "THB/KRW",
      "label": "THB/KRW",
      "price": 46.142,
      "dod": -0.14283240997228921,
      "mom": -0.39718516599749054,
      "yoy": 8.147002296910905,
      "raw_points": 1280
    }
  ]
}