{
  "generated_at": "2026-03-04T05:15:52.298002+00:00",
  "insight": "Raw data summary: NASDAQ -1.02%, S&P 500 -0.94%, KOSPI -9.72%, USD/KRW +2.35%",
  "errors": [],
  "items": [
    {
      "key": "NASDAQ",
      "label": "NASDAQ",
      "price": 22516.689453125,
      "dod": -1.020578298225117,
      "mom": -4.028378219534197,
      "yoy": 22.705487649831614,
      "raw_points": 1255
    },
    {
      "key": "S&P500",
      "label": "S&P 500",
      "price": 6816.6298828125,
      "dod": -0.9444031095625391,
      "mom": -1.7639339523456716,
      "yoy": 16.529160924914027,
      "raw_points": 1255
    },
    {
      "key": "KOSPI",
      "label": "KOSPI",
      "price": 5229.16015625,
      "dod": -9.716138282855464,
      "mom": 5.646643893157332,
      "yoy": 106.77444592128403,
      "raw_points": 1223
    },
    {
      "key": "KOSDAQ",
      "label": "KOSDAQ",
      "price": 1013.72998046875,
      "dod": -10.896543554865335,
      "mom": -7.705124550374453,
      "yoy": 37.38039665654074,
      "raw_points": 1222
    },
    {
      "key": "SET Index",
      "label": "SET Index",
      "price": 1362.5699462890625,
      "dod": -7.087579544934304,
      "mom": 3.114066759642175,
      "yoy": 15.70343477975588,
      "raw_points": 1207
    },
    {
      "key": "BTC/USD",
      "label": "BTC/USD",
      "price": 67862.6328125,
      "dod": -1.3278188917371865,
      "mom": -13.758168305871171,
      "yoy": -22.195683599384868,
      "raw_points": 1826
    },
    {
      "key": "BTC/KRW",
      "label": "BTC/KRW",
      "price": 100473800.0,
      "dod": 0.5243114560204212,
      "mom": -12.161838929841373,
      "yoy": -20.76638147322934,
      "raw_points": 1826
    },
    {
      "key": "DXY",
      "label": "Dollar Index",
      "price": 99.18699645996094,
      "dod": 0.13830732355610342,
      "mom": 1.6156088922738252,
      "yoy": -6.1972777909936925,
      "raw_points": 1258
    },
    {
      "key": "USD/JPY",
      "label": "USD/JPY",
      "price": 157.55,
      "dod": 1.0713369258404004,
      "mom": 2.638436482084698,
      "yoy": 5.124441182358048,
      "raw_points": 262
    },
    {
      "key": "USD/KRW",
      "label": "USD/KRW",
      "price": 1470.27,
      "dod": 2.3544153990741017,
      "mom": 2.2263167043281755,
      "yoy": 2.1183939101384253,
      "raw_points": 262
    },
    {
      "key": "USD/THB",
      "label": "USD/THB",
      "price": 31.634,
      "dod": 1.8381997875285758,
      "mom": 1.4430477167778324,
      "yoy": -6.416590243469505,
      "raw_points": 262
    },
    {
      "key": "THB/KRW",
      "label": "THB/KRW",
      "price": 46.477,
      "dod": 0.5081960122832045,
      "mom": 0.7718826564905239,
      "yoy": 9.118869297771917,
      "raw_points": 262
    }
  ]
}